[
  {
    "full_name": "samber/mo",
    "stargazers_count": 969,
    "open_issues_count": 5,
    "forks_count": 24
  },
  {
    "full_name": "nix-community/todomvc-nix",
    "stargazers_count": 127,
    "open_issues_count": 12,
    "forks_count": 22
  },
  {
    "full_name": "qazbnm456/awesome-web-security",
    "stargazers_count": 8696,
    "open_issues_count": 25,
    "forks_count": 1485
  },
  {
    "full_name": "nix-community/linuxkit-nix",
    "stargazers_count": 122,
    "open_issues_count": 8,
    "forks_count": 26
  },
  {
    "full_name": "nix-community/dream2nix",
    "stargazers_count": 272,
    "open_issues_count": 67,
    "forks_count": 52
  },
  {
    "full_name": "railwayapp/nixpacks",
    "stargazers_count": 1159,
    "open_issues_count": 40,
    "forks_count": 45
  },
  {
    "full_name": "pveyes/raw.macro",
    "stargazers_count": 143,
    "open_issues_count": 0,
    "forks_count": 9
  },
  {
    "full_name": "arlyon/stailwc",
    "stargazers_count": 62,
    "open_issues_count": 3,
    "forks_count": 0
  },
  {
    "full_name": "rakeshpai/fast-fp.macro",
    "stargazers_count": 92,
    "open_issues_count": 9,
    "forks_count": 4
  },
  {
    "full_name": "knpwrs/ms.macro",
    "stargazers_count": 190,
    "open_issues_count": 9,
    "forks_count": 6
  },
  {
    "full_name": "Xe/site",
    "stargazers_count": 424,
    "open_issues_count": 15,
    "forks_count": 90
  },
  {
    "full_name": "tadfisher/android-nixpkgs",
    "stargazers_count": 78,
    "open_issues_count": 6,
    "forks_count": 21
  },
  {
    "full_name": "tamagui/tamagui",
    "stargazers_count": 2362,
    "open_issues_count": 23,
    "forks_count": 53
  },
  {
    "full_name": "cachix/cachix",
    "stargazers_count": 482,
    "open_issues_count": 89,
    "forks_count": 33
  },
  {
    "full_name": "evilfactorylabs/area13",
    "stargazers_count": 1,
    "open_issues_count": 0,
    "forks_count": 0
  },
  {
    "full_name": "ducktors/turborepo-remote-cache",
    "stargazers_count": 199,
    "open_issues_count": 4,
    "forks_count": 24
  },
  {
    "full_name": "0xInfection/Awesome-WAF",
    "stargazers_count": 4668,
    "open_issues_count": 0,
    "forks_count": 884
  },
  {
    "full_name": "ulixee/secret-agent",
    "stargazers_count": 530,
    "open_issues_count": 44,
    "forks_count": 37
  },
  {
    "full_name": "nix-community/rnix-parser",
    "stargazers_count": 226,
    "open_issues_count": 6,
    "forks_count": 32
  },
  {
    "full_name": "joshbuchea/HEAD",
    "stargazers_count": 29357,
    "open_issues_count": 19,
    "forks_count": 1962
  },
  {
    "full_name": "BuilderIO/mitosis",
    "stargazers_count": 6393,
    "open_issues_count": 84,
    "forks_count": 243
  },
  {
    "full_name": "gergoerdi/functional-mos6502-web-performance",
    "stargazers_count": 17,
    "open_issues_count": 2,
    "forks_count": 4
  },
  {
    "full_name": "soywod/himalaya",
    "stargazers_count": 2032,
    "open_issues_count": 41,
    "forks_count": 57
  },
  {
    "full_name": "urfave/cli",
    "stargazers_count": 19036,
    "open_issues_count": 124,
    "forks_count": 1616
  },
  {
    "full_name": "brainfucksec/neovim-lua",
    "stargazers_count": 511,
    "open_issues_count": 1,
    "forks_count": 91
  },
  {
    "full_name": "webauthn-open-source/webauthn-simple-app",
    "stargazers_count": 120,
    "open_issues_count": 7,
    "forks_count": 18
  },
  {
    "full_name": "herrjemand/awesome-webauthn",
    "stargazers_count": 693,
    "open_issues_count": 3,
    "forks_count": 69
  },
  {
    "full_name": "fly-hiring/platform-challenge",
    "stargazers_count": 5,
    "open_issues_count": 1,
    "forks_count": 2
  },
  {
    "full_name": "dolthub/dolt",
    "stargazers_count": 13039,
    "open_issues_count": 231,
    "forks_count": 372
  },
  {
    "full_name": "vic/mk-darwin-system",
    "stargazers_count": 53,
    "open_issues_count": 4,
    "forks_count": 6
  }
]