[
  {
    "full_name": "lucidph3nx/nvim-sops",
    "stargazers_count": 3,
    "open_issues_count": 0,
    "forks_count": 0
  },
  {
    "full_name": "ray-x/navigator.lua",
    "stargazers_count": 1096,
    "open_issues_count": 14,
    "forks_count": 54
  },
  {
    "full_name": "chakra-ui/panda",
    "stargazers_count": 3548,
    "open_issues_count": 11,
    "forks_count": 123
  },
  {
    "full_name": "laptou/jsi-rs",
    "stargazers_count": 76,
    "open_issues_count": 0,
    "forks_count": 4
  },
  {
    "full_name": "mobile-dev-inc/maestro",
    "stargazers_count": 4418,
    "open_issues_count": 273,
    "forks_count": 171
  },
  {
    "full_name": "bamlab/flashlight",
    "stargazers_count": 760,
    "open_issues_count": 10,
    "forks_count": 17
  },
  {
    "full_name": "bigskysoftware/htmx",
    "stargazers_count": 21655,
    "open_issues_count": 284,
    "forks_count": 767
  },
  {
    "full_name": "thi-ng/umbrella",
    "stargazers_count": 3025,
    "open_issues_count": 65,
    "forks_count": 136
  },
  {
    "full_name": "smol-ai/developer",
    "stargazers_count": 11073,
    "open_issues_count": 75,
    "forks_count": 1068
  },
  {
    "full_name": "erikthedeveloper/code-review-emoji-guide",
    "stargazers_count": 391,
    "open_issues_count": 4,
    "forks_count": 25
  },
  {
    "full_name": "Julow/nix-opam-switch",
    "stargazers_count": 4,
    "open_issues_count": 0,
    "forks_count": 0
  },
  {
    "full_name": "homanp/superagent",
    "stargazers_count": 2593,
    "open_issues_count": 40,
    "forks_count": 467
  },
  {
    "full_name": "melange-re/melange-re.github.io",
    "stargazers_count": 17,
    "open_issues_count": 20,
    "forks_count": 5
  },
  {
    "full_name": "mobily/ts-belt",
    "stargazers_count": 917,
    "open_issues_count": 27,
    "forks_count": 24
  },
  {
    "full_name": "nixified-ai/flake",
    "stargazers_count": 340,
    "open_issues_count": 24,
    "forks_count": 31
  },
  {
    "full_name": "nix-community/nixvim",
    "stargazers_count": 470,
    "open_issues_count": 13,
    "forks_count": 74
  },
  {
    "full_name": "radio24/TorBox",
    "stargazers_count": 216,
    "open_issues_count": 10,
    "forks_count": 25
  },
  {
    "full_name": "lxsmnsyc/forgetti",
    "stargazers_count": 285,
    "open_issues_count": 5,
    "forks_count": 6
  },
  {
    "full_name": "numtide/system-manager",
    "stargazers_count": 352,
    "open_issues_count": 7,
    "forks_count": 8
  },
  {
    "full_name": "NixOS/hydra",
    "stargazers_count": 896,
    "open_issues_count": 372,
    "forks_count": 286
  },
  {
    "full_name": "DZakh/rescript-struct",
    "stargazers_count": 94,
    "open_issues_count": 1,
    "forks_count": 4
  },
  {
    "full_name": "cometkim/rescript-vitest",
    "stargazers_count": 37,
    "open_issues_count": 2,
    "forks_count": 5
  },
  {
    "full_name": "pd4d10/vite-plugin-svgr",
    "stargazers_count": 370,
    "open_issues_count": 22,
    "forks_count": 47
  },
  {
    "full_name": "ElMassimo/vite-plugin-environment",
    "stargazers_count": 123,
    "open_issues_count": 0,
    "forks_count": 7
  },
  {
    "full_name": "itsMapleLeaf/vite-plugin-babel-macros",
    "stargazers_count": 46,
    "open_issues_count": 0,
    "forks_count": 5
  },
  {
    "full_name": "getsentry/sentry-javascript-bundler-plugins",
    "stargazers_count": 85,
    "open_issues_count": 28,
    "forks_count": 21
  },
  {
    "full_name": "vitejs/vite-plugin-react-swc",
    "stargazers_count": 560,
    "open_issues_count": 7,
    "forks_count": 31
  },
  {
    "full_name": "vitejs/awesome-vite",
    "stargazers_count": 11441,
    "open_issues_count": 30,
    "forks_count": 951
  },
  {
    "full_name": "vitejs/vite",
    "stargazers_count": 59992,
    "open_issues_count": 583,
    "forks_count": 5355
  },
  {
    "full_name": "aantron/hyper",
    "stargazers_count": 58,
    "open_issues_count": 3,
    "forks_count": 2
  }
]